mpegdash/__init__.py
mpegdash/nodes.py
mpegdash/parser.py
mpegdash/prettyprinter.py
mpegdash/utils.py
mpegdash-0.3.1.dist-info/LICENSE
mpegdash-0.3.1.dist-info/METADATA
mpegdash-0.3.1.dist-info/WHEEL
mpegdash-0.3.1.dist-info/top_level.txt
mpegdash-0.3.1.dist-info/RECORD
