Metadata-Version: 2.1
Name: mpegdash
Version: 0.3.1
Summary: MPEG-DASH MPD(Media Presentation Description) Parser
Home-page: https://github.com/sangwonl/python-mpegdash
Author: sangwonl
Author-email: gamzabaw@gmail.com
License: MIT
Platform: UNKNOWN
Classifier: Programming Language :: Python
Classifier: Programming Language :: Python :: 3
Classifier: Environment :: Other Environment
Classifier: Intended Audience :: Developers
Classifier: License :: OSI Approved :: MIT License
Classifier: Operating System :: OS Independent
Classifier: Topic :: Software Development :: Libraries :: Python Modules
License-File: LICENSE
